{
  "name": "bcdui",
  "version": "5.0.0",
  "author":      "BusinessCode GmbH, Germany",
  "license":     "Apache V2.0",
  "dependencies": {
    "jsdoc":                "3.6.7",
    "jaguarjs-jsdoc":       "1.1.0",
    "node-sass":            "4.7.2",
    "clean-css-cli":        "4.1.9",
    "@babel/core":          "7.14.0",
    "@babel/cli":           "7.13.16",
    "@babel/preset-env":    "7.14.1",
    "babel-preset-minify":  "0.4.2",
    "jison":                "0.4.18"
  },
  "browserslist": [
    "IE 11"
  ]
}